Metadata-Version: 2.1
Name: L-SpaceCurves
Version: 0.0.8
Summary: Space filling curves in python
Home-page: UNKNOWN
Author: Thiago Santos
Author-email: tthiagosantos38@gmail.com
License: MIT License
Keywords: Peano,Hilbert
Platform: UNKNOWN
